forgesentry/__init__.py
forgesentry/apps.py
forgesentry/middleware.py
forgesentry/settings.py
forgesentry/templates/sentry/js.html
forgesentry/templatetags/__init__.py
forgesentry/templatetags/sentry.py
forge_sentry-0.3.0.dist-info/METADATA
forge_sentry-0.3.0.dist-info/WHEEL
forge_sentry-0.3.0.dist-info/RECORD
